<?xml version='1.0' encoding='utf-8'?>
<odoo>
    <data>
        <record id="property_management_tree" model="ir.ui.view">
            <field name="name">Property Management Tree</field>
            <field name="model">new_fields.main.property</field>
            <field name="arch" type="xml">
                <tree>
                    <field name="name"/>
                    <field name="code"/>
                    <field name="project"/>
                    <field name="total_cost"/>
                    <field name="date"/>
                    <field name="launch_date"/>
                </tree>
            </field>
        </record>
    </data>
</odoo>
